equations/__init__.py
equations/__main__.py
equations-1.0.0.dist-info/DESCRIPTION.rst
equations-1.0.0.dist-info/METADATA
equations-1.0.0.dist-info/RECORD
equations-1.0.0.dist-info/WHEEL
equations-1.0.0.dist-info/metadata.json
equations-1.0.0.dist-info/top_level.txt
